{
  "type": "FeatureCollection",
  "features": [
    {
      "type": "Feature",
      "properties": {},
      "geometry": {
        "type": "Polygon",
        "coordinates": [
          [
            [
              114.17069435119627,
              22.294496710081507
            ],
            [
              114.16803359985352,
              22.302755575548254
            ],
            [
              114.17438507080078,
              22.303470262105765
            ],
            [
              114.17721748352051,
              22.302914395099272
            ],
            [
              114.1750717163086,
              22.294814367780518
            ],
            [
              114.17069435119627,
              22.294496710081507
            ]
          ]
        ]
      }
    },
    {
      "type": "Feature",
      "properties": {},
      "geometry": {
        "type": "Polygon",
        "coordinates": [
          [
            [
              114.17721748352051,
              22.303073214469702
            ],
            [
              114.17876243591309,
              22.305693708009834
            ],
            [
              114.1742992401123,
              22.307361269208684
            ],
            [
              114.17146682739258,
              22.3052966666944
            ],
            [
              114.17163848876953,
              22.303073214469702
            ],
            [
              114.17438507080078,
              22.303629080844164
            ],
            [
              114.17721748352051,
              22.303073214469702
            ]
          ]
        ]
      }
    },
    {
      "type": "Feature",
      "properties": {},
      "geometry": {
        "type": "Polygon",
        "coordinates": [
          [
            [
              114.17155265808105,
              22.305534891619104
            ],
            [
              114.16580200195311,
              22.318557235804306
            ],
            [
              114.16245460510254,
              22.318001428857198
            ],
            [
              114.16125297546387,
              22.326497093368353
            ],
            [
              114.17876243591309,
              22.326814678273763
            ],
            [
              114.17790412902832,
              22.322686018117693
            ],
            [
              114.17421340942383,
              22.30728186198407
            ],
            [
              114.17155265808105,
              22.305534891619104
            ]
          ]
        ]
      }
    },
    {
      "type": "Feature",
      "properties": {},
      "geometry": {
        "type": "Polygon",
        "coordinates": [
          [
            [
              114.18880462646483,
              22.324353376348228
            ],
            [
              114.18743133544922,
              22.321574434895677
            ],
            [
              114.18751716613768,
              22.310616926540913
            ],
            [
              114.19137954711914,
              22.311728597025354
            ],
            [
              114.19498443603516,
              22.320224643365446
            ],
            [
              114.18880462646483,
              22.324353376348228
            ]
          ]
        ]
      }
    }
  ]
}